{
  "updated_at": "2026-07-17T13:24:57+08:00",
  "city": "杭州",
  "source": "https://sunsetbot.top/",
  "today_sunrise": {
    "GFS": {
      "quality": 0.241,
      "level": "小烧到中烧",
      "aod": 0.244,
      "event_time": "2026-07-17 05:09:59",
      "model_time": "2026071612z"
    },
    "EC": {
      "quality": 0.355,
      "level": "小烧到中烧",
      "aod": 0.269,
      "event_time": "2026-07-17 05:09:59",
      "model_time": "2026071512z"
    }
  },
  "today_sunset": {
    "GFS": {
      "quality": 0.003,
      "level": "微微烧",
      "aod": 0.529,
      "event_time": "2026-07-17 19:00:19",
      "model_time": "2026071700z"
    },
    "EC": {
      "quality": 0.009,
      "level": "微微烧",
      "aod": 0.515,
      "event_time": "2026-07-17 19:00:19",
      "model_time": "2026071612z"
    }
  },
  "tomorrow_sunrise": {
    "GFS": {
      "quality": 0.105,
      "level": "小烧",
      "aod": 0.284,
      "event_time": "2026-07-18 05:10:32",
      "model_time": "2026071618z"
    },
    "EC": {
      "quality": 0.001,
      "level": "微微烧",
      "aod": 0.39,
      "event_time": "2026-07-18 05:10:32",
      "model_time": "2026071612z"
    }
  },
  "tomorrow_sunset": {
    "GFS": {
      "quality": 0,
      "level": "不烧",
      "aod": 0.608,
      "event_time": "2026-07-18 18:59:55",
      "model_time": "2026071618z"
    },
    "EC": {
      "quality": 0.091,
      "level": "小烧",
      "aod": 0.563,
      "event_time": "2026-07-18 18:59:55",
      "model_time": "2026071612z"
    }
  },
  "meta": {
    "successful_selections": 8,
    "captured_json_responses": 14,
    "failures": []
  }
}
